spice_stew/__init__.py
spice_stew/spice_stew.py
spice_stew-2022.6.23.dist-info/LICENSE.txt
spice_stew-2022.6.23.dist-info/METADATA
spice_stew-2022.6.23.dist-info/WHEEL
spice_stew-2022.6.23.dist-info/entry_points.txt
spice_stew-2022.6.23.dist-info/top_level.txt
spice_stew-2022.6.23.dist-info/RECORD
