Metadata-Version: 2.1
Name: spice-stew
Version: 2022.6.23
Summary: Correct the pointing of SOLO/SPICE with SPICE kernels
Home-page: https://github.com/gpelouze/spice_stew
Author: Gabriel Pelouze
Author-email: gabriel.pelouze@universite-paris-saclay.fr
License: UNKNOWN
Platform: UNKNOWN
Classifier: Programming Language :: Python :: 3
Classifier: License :: OSI Approved :: MIT License
Classifier: Operating System :: OS Independent
Classifier: Intended Audience :: Science/Research
Classifier: Topic :: Scientific/Engineering :: Astronomy
Requires-Python: >=3.6
License-File: LICENSE.txt
Requires-Dist: astropy (>=4.3.1)
Requires-Dist: numpy (>=1.21.4)
Requires-Dist: scipy (>=1.1.0)
Requires-Dist: spiceypy (>=4.0.3)
Requires-Dist: tqdm (>=4.62.3)
Requires-Dist: matplotlib (>=3.0.2)
